{
    "Changes": [
        {
            "LogName": "Add universal tastes",
            "Action": "EditData",
            "Target": "Data/NPCGiftTastes",
            "TextOperations": [
                 {
                    "Operation": "Append",
                    "Target": ["Entries", "Universal_Neutral"],
                    "Value": "{{ModId}}_AncientFruitPie {{ModId}}_BananaPie {{ModId}}_BlackberryPie {{ModId}}_BlueberryPie {{ModId}}_CactusFruitPie {{ModId}}_CoconutPie {{ModId}}_CranberryPie {{ModId}}_CrystalFruitPie {{ModId}}_GrapePie {{ModId}}_MangoPie {{ModId}}_MelonPie {{ModId}}_PineapplePie {{ModId}}_SalmonberryPie {{ModId}}_SpiceBerryPie {{ModId}}_StarfruitPie {{ModId}}_StrawberryPie {{ModId}}_WildPlumPie {{ModId}}_AncientFruitJam {{ModId}}_BananaJam {{ModId}}_BlackberryJam {{ModId}}_BlueberryJam {{ModId}}_CactusFruitJam {{ModId}}_CoconutJam {{ModId}}_CranberryJam {{ModId}}_CrystalFruitJam {{ModId}}_GrapeJam {{ModId}}_MangoJam {{ModId}}_MelonJam {{ModId}}_PineappleJam {{ModId}}_SalmonberryJam {{ModId}}_SpiceBerryJam {{ModId}}_StarfruitJam {{ModId}}_StrawberryJam {{ModId}}_WildPlumJam",
                    "Delimiter": " "
                }
            ]
        },
        
        {
            "LogName": "Add gift tastes for Abigail",
            "Action": "EditData",
            "Target": "Data/NPCGiftTastes",
            "TextOperations": [
                {
                    "Operation": "Append",
                    "Target": ["Fields", "Abigail", 5],
                    "Value": "jams_and_pies_object",
                    "Delimiter": " "
                },
                {
                    "Operation": "Append",
                    "Target": ["Fields", "Abigail", 1],
                    "Value": "{{ModId}}_ApplePie {{ModId}}_AppleJam",
                    "Delimiter": " "
                },
                {
                    "Operation": "Append",
                    "Target": ["Fields", "Abigail", 3],
                    "Value": "{{ModId}}_ApricotPie {{ModId}}CherryPie {{ModId}}_OrangePie {{ModId}}_PeachPie {{ModId}}_PomegranatePie {{ModId}}_ApricotJam {{ModId}}_CherryJam {{ModId}}_OrangeJam{{ModId}}_PeachJam {{ModId}}_PomegranateJam",
                    "Delimiter": " "
                },
                {
                    "Operation": "Append",
                    "Target": ["Fields", "Abigail", 9],
                    "Value": "{{ModId}}_SalmonberryPie {{ModId}}_SalmonberryJam",
                    "Delimiter": " "
                }
            ]
        },
        {
            "LogName": "Add gift tastes for Demetrius",
            "Action": "EditData",
            "Target": "Data/NPCGiftTastes",
            "TextOperations": [
                {
                    "Operation": "Append",
                    "Target": ["Fields", "Demetrius", 3],
                    "Value": "jams_and_pies_object",
                    "Delimiter": " "
                },
                {
                    "Operation": "Append",
                    "Target": ["Fields", "Demetrius", 1],
                    "Value": "{{ModId}}_AncientFruitPie {{ModId}}_PineapplePie {{ModId}}_AncientFruitJam {{ModId}}_PineappleJam",
                    "Delimiter": " "
                }
            ]
        },
        {
            "LogName": "Add gift tastes for Elliott",
            "Action": "EditData",
            "Target": "Data/NPCGiftTastes",
            "TextOperations": [
                {
                    "Operation": "Append",
                    "Target": ["Fields", "Elliott", 3],
                    "Value": "jams_and_pies_object",
                    "Delimiter": " "
                },
                {
                    "Operation": "Append",
                    "Target": ["Fields", "Elliott", 1],
                    "Value": "{{ModId}}_ApricotPie {{ModId}}_CrystalFruitPie {{ModId}}_PomegranatePie {{ModId}}_ApricotJam {{ModId}}_CrystalFruitJam {{ModId}}_PomegranateJam",
                    "Delimiter": " "
                }
            ]
        },
        {
            "LogName": "Add gift tastes for Emily",
            "Action": "EditData",
            "Target": "Data/NPCGiftTastes",
            "TextOperations": [
                {
                    "Operation": "Append",
                    "Target": ["Fields", "Emily", 1],
                    "Value": "{{ModId}}_ApplePie {{ModId}}_AppleJam",
                    "Delimiter": " "
                }
            ]
        },
        {
            "LogName": "Add gift tastes for Evelyn",
            "Action": "EditData",
            "Target": "Data/NPCGiftTastes",
            "TextOperations": [
                {
                    "Operation": "Append",
                    "Target": ["Fields", "Evelyn", 1],
                    "Value": "{{ModId}}_ApricotPie {{ModId}}_ApricotJam",
                    "Delimiter": " "
                },
                {
                    "Operation": "Append",
                    "Target": ["Fields", "Evelyn", 7],
                    "Value": "{{ModId}}_SpiceBerryPie {{ModId}}_SpiceBerryJam",
                    "Delimiter": " "
                }
            ]
        },
        {
            "LogName": "Add gift tastes for Gus",
            "Action": "EditData",
            "Target": "Data/NPCGiftTastes",
            "TextOperations": [
                {
                    "Operation": "Append",
                    "Target": ["Fields", "Gus", 3],
                    "Value": "jams_and_pies_object",
                    "Delimiter": " "
                },
                {
                    "Operation": "Append",
                    "Target": ["Fields", "Gus", 1],
                    "Value": "{{ModId}}_CranberryPie {{ModId}}_OrangePie {{ModId}}_CranberryJam {{ModId}}_OrangeJam",
                    "Delimiter": " "
                },
                {
                    "Operation": "Append",
                    "Target": ["Fields", "Gus", 9],
                    "Value": "{{ModId}}_GrapePie {{ModId}}_MangoPie {{ModId}}_MelonPie {{ModId}}_PineapplePie {{ModId}}_SalmonberryPie {{ModId}}_SpiceBerryPie {{ModId}}_StarfruitPie {{ModId}}_GrapeJam {{ModId}}_MangoJam {{ModId}}_MelonJam {{ModId}}_PineappleJam {{ModId}}_SalmonberryJam {{ModId}}_SpiceBerryJam {{ModId}}_StarfruitJam",
                    "Delimiter": " "
                }
            ]
        },
        {
            "LogName": "Add gift tastes for Haley",
            "Action": "EditData",
            "Target": "Data/NPCGiftTastes",
            "TextOperations": [
                {
                    "Operation": "Append",
                    "Target": ["Fields", "Haley", 1],
                    "Value": "{{ModId}}_CherryPie {{ModId}}_CoconutPie",
                    "Delimiter": " "
                },
                {
                    "Operation": "Append",
                    "Target": ["Fields", "Haley", 5],
                    "Value": "{{ModId}}_AncientFruitPie {{ModId}}_BananaPie {{ModId}}_BlackberryPie {{ModId}}_BlueberryPie {{ModId}}_CactusFruitPie {{ModId}}_CranberryPie {{ModId}}_CrystalFruitPie {{ModId}}_GrapePie {{ModId}}_MangoPie {{ModId}}_MelonPie {{ModId}}_PineapplePie {{ModId}}_StarfruitPie {{ModId}}_StrawberryPie {{ModId}}_WildPlumPie {{ModId}}_AncientFruitJam {{ModId}}_BananaJam {{ModId}}_BlackberryJam {{ModId}}_BlueberryJam {{ModId}}_CactusFruitJam {{ModId}}_CranberryJam {{ModId}}_CrystalFruitJam {{ModId}}_GrapeJam {{ModId}}_MangoJam {{ModId}}_MelonJam {{ModId}}_PineappleJam {{ModId}}_StarfruitJam {{ModId}}_StrawberryJam {{ModId}}_WildPlumJam",
                    "Delimiter": " "
                }
            ]
        },
        {
            "LogName": "Add gift tastes for Harvey",
            "Action": "EditData",
            "Target": "Data/NPCGiftTastes",
            "TextOperations": [
                  {
                    "Operation": "Append",
                    "Target": ["Fields", "Harvey", 3],
                    "Value": "jams_and_pies_object",
                    "Delimiter": " "
                },
                {
                    "Operation": "Append",
                    "Target": ["Fields", "Harvey", 1],
                    "Value": "{{ModId}}_BlueberryPie {{ModId}}_CranberryPie {{ModId}}_BlueberryJam {{ModId}}_CranberryJam",
                    "Delimiter": " "
                },
                {
                    "Operation": "Append",
                    "Target": ["Fields", "Harvey", 5],
                    "Value": "{{ModId}}_SalmonberryPie {{ModId}}_SpiceBerryPie {{ModId}}_SalmonberryJam {{ModId}}_SpiceBerryJam",
                    "Delimiter": " "
                }
            ]
        },
        {
            "LogName": "Add gift tastes for Jas",
            "Action": "EditData",
            "Target": "Data/NPCGiftTastes",
            "TextOperations": [
                {
                    "Operation": "Append",
                    "Target": ["Fields", "Jas", 5],
                    "Value": "jams_and_pies_object",
                    "Delimiter": " "
                },           
                {
                    "Operation": "Append",
                    "Target": ["Fields", "Jas", 3],
                    "Value": "{{ModId}}_ApplePie {{ModId}}_ApricotPie {{ModId}}_CherryPie {{ModId}}_CoconutPie {{ModId}}_CrystalFruitPie {{ModId}}_OrangePie {{ModId}}_PeachPie {{ModId}}_PomegranatePie {{ModId}}_AppleJam {{ModId}}_ApricotJam {{ModId}}_CrystalFruitJam {{ModId}}_CherryJam {{ModId}}_CoconutJam {{ModId}}_OrangeJam {{ModId}}_PeachJam {{ModId}}_PomegranateJam",
                    "Delimiter": " "
                },
                {
                    "Operation": "Append",
                    "Target": ["Fields", "Jas", 9],
                    "Value": "{{ModId}}_SalmonberryPie {{ModId}}_SpiceBerryPie {{ModId}}_SalmonberryJam {{ModId}}_SpiceBerryJam",
                    "Delimiter": " "
                }
            ]
        },
        {
            "LogName": "Add gift tastes for Jodi",
            "Action": "EditData",
            "Target": "Data/NPCGiftTastes",
            "TextOperations": [
                {
                    "Operation": "Append",
                    "Target": ["Fields", "Jodi", 3],
                    "Value": "jams_and_pies_object",
                    "Delimiter": " "
                },
                {
                    "Operation": "Append",
                    "Target": ["Fields", "Jodi", 1],
                    "Value": "{{ModId}}_CrystalFruitPie {{ModId}}_PomegranatePie {{ModId}}_CrystalFruitJam {{ModId}}_PomegranateJam",
                    "Delimiter": " "
                },
                {
                    "Operation": "Append",
                    "Target": ["Fields", "Jodi", 7],
                    "Value": "{{ModId}}_SpiceBerryPie {{ModId}}_SpiceBerryJam",
                    "Delimiter": " "
                }
            ]
        },
        {
            "LogName": "Add gift tastes for Kent",
            "Action": "EditData",
            "Target": "Data/NPCGiftTastes",
            "TextOperations": [
                {
                    "Operation": "Append",
                    "Target": ["Fields", "Kent", 3],
                    "Value": "jams_and_pies_object",
                    "Delimiter": " "
                },
                {
                    "Operation": "Append",
                    "Target": ["Fields", "Kent", 1],
                    "Value": "{{ModId}}_BananaPie {{ModId}}_BlackberryPie {{ModId}}_SalmonberryPie {{ModId}}_StarfruitPie {{ModId}}_BananaJam {{ModId}}_BlackberryJam {{ModId}}_SalmonberryJam {{ModId}}_StarfruitJam",
                    "Delimiter": " "
                }
            ]
        },
        {
            "LogName": "Add gift tastes for Krobus",
            "Action": "EditData",
            "Target": "Data/NPCGiftTastes",
            "TextOperations": [
                {
                    "Operation": "Append",
                    "Target": ["Fields", "Krobus", 1],
                    "Value": "{{ModId}}_PeachPie {{ModId}}_PeachJam",
                    "Delimiter": " "
                }
            ]
        },
        {
            "LogName": "Add gift tastes for Leah",
            "Action": "EditData",
            "Target": "Data/NPCGiftTastes",
            "TextOperations": [
                {
                    "Operation": "Append",
                    "Target": ["Fields", "Leah", 3],
                    "Value": "jams_and_pies_object",
                    "Delimiter": " "
                },
                {
                    "Operation": "Append",
                    "Target": ["Fields", "Leah", 1],
                    "Value": "{{ModId}}_AncientFruitPie {{ModId}}_CrystalFruitPie {{ModId}}_GrapePie {{ModId}}_MangoPie {{ModId}}_PeachPie {{ModId}}_AncientFruitJam {{ModId}}_CrystalFruitJam {{ModId}}_GrapeJam {{ModId}}_MangoJam {{ModId}}_PeachJam",
                    "Delimiter": " "
                },
                {
                    "Operation": "Append",
                    "Target": ["Fields", "Leah", 9],
                    "Value": "{{ModId}}_CactusFruitPie {{ModId}}_CoconutPie {{ModId}}_CranberryPie {{ModId}}_MelonPie {{ModId}}_PineapplePie {{ModId}}_SalmonberryPie {{ModId}}_StrawberryPie  {{ModId}}_CactusFruitJam {{ModId}}_CoconutJam {{ModId}}_CranberryJam {{ModId}}_MelonJam {{ModId}}_PineappleJam {{ModId}}_SalmonberryJam {{ModId}}_StrawberryJam",
                    "Delimiter": " "
                }
            ]
        },
        {
            "LogName": "Add gift tastes for Leo",
            "Action": "EditData",
            "Target": "Data/NPCGiftTastes",
            "TextOperations": [
                {
                    "Operation": "Append",
                    "Target": ["Fields", "Leo", 5],
                    "Value": "jams_and_pies_object",
                    "Delimiter": " "
                },
                {
                    "Operation": "Append",
                    "Target": ["Fields", "Leo", 1],
                    "Value": "{{ModId}}_BananaPie {{ModId}}_MangoPie {{ModId}}_BananaJam {{ModId}}_MangoJam",
                    "Delimiter": " "
                },
                {
                    "Operation": "Append",
                    "Target": ["Fields", "Leo", 3],
                    "Value": "{{ModId}}_ApricotPie {{ModId}}_CherryPie {{ModId}}_CrystalFruitPie {{ModId}}_OrangePie {{ModId}}_PeachPie {{ModId}}_PomegranatePie {{ModId}}_SpiceBerryPie {{ModId}}_ApricotJam {{ModId}}_CherryJam {{ModId}}_CrystalFruitJam {{ModId}}_OrangeJam {{ModId}}_PeachJam {{ModId}}_PomegranateJam {{ModId}}_SpiceBerryJam",
                    "Delimiter": " "
                },
                {
                    "Operation": "Append",
                    "Target": ["Fields", "Leo", 9],
                    "Value": "{{ModId}}_SalmonberryPie {{ModId}}_SalmonberryJam ",
                    "Delimiter": " "
                }
            ]
        },
        {
            "LogName": "Add gift tastes for Lewis",
            "Action": "EditData",
            "Target": "Data/NPCGiftTastes",
            "TextOperations": [
                {
                    "Operation": "Append",
                    "Target": ["Fields", "Lewis", 1],
                    "Value": "{{ModId}}_CherryPie {{ModId}}_CherryJam",
                    "Delimiter": " "
                }
            ]
        },
        {
            "LogName": "Add gift tastes for Linus",
            "Action": "EditData",
            "Target": "Data/NPCGiftTastes",
            "TextOperations": [
                {
                    "Operation": "Append",
                    "Target": ["Fields", "Linus", 3],
                    "Value": "jams_and_pies_object",
                    "Delimiter": " "
                },
                {
                    "Operation": "Append",
                    "Target": ["Fields", "Linus", 1],
                    "Value": "{{ModId}}_BlueberryPie {{ModId}}_CactusFruitPie {{ModId}}_CranberryPie {{ModId}}_WildPlumPie {{ModId}}_BlueberryJam {{ModId}}_CactusFruitJam {{ModId}}_CranberryJam {{ModId}}_WildPlumJam",
                    "Delimiter": " "
                }
            ]
        },
        {
            "LogName": "Add gift tastes for Maru",
            "Action": "EditData",
            "Target": "Data/NPCGiftTastes",
            "TextOperations": [
                {
                    "Operation": "Append",
                    "Target": ["Fields", "Maru", 5],
                    "Value": "{{ModId}}_BlueberryPie {{ModId}}_CrystalFruitPie {{ModId}}_BlueberryJam {{ModId}}_CrystalFruitJam",
                    "Delimiter": " "
                }
            ]
        },
        {
            "LogName": "Add gift tastes for Pam",
            "Action": "EditData",
            "Target": "Data/NPCGiftTastes",
            "TextOperations": [
                {
                    "Operation": "Append",
                    "Target": ["Fields", "Pam", 3],
                    "Value": "jams_and_pies_object",
                    "Delimiter": " "
                },
                {
                    "Operation": "Append",
                    "Target": ["Fields", "Pam", 1],
                    "Value": "{{ModId}}_CactusFruitPie {{ModId}}_CactusFruitJam"
                }
            ]
        },
        {
            "LogName": "Add gift tastes for Penny",
            "Action": "EditData",
            "Target": "Data/NPCGiftTastes",
            "TextOperations": [
                {
                    "Operation": "Append",
                    "Target": ["Fields", "Penny", 1],
                    "Value": "{{ModId}}_MelonPie {{ModId}}_OrangePie {{ModId}}_MelonJam {{ModId}}_OrangeJam",
                    "Delimiter": " "
                },
                {
                    "Operation": "Append",
                    "Target": ["Fields", "Penny", 7],
                    "Value": "{{ModId}}_GrapePie {{ModId}}_GrapeJam",
                    "Delimiter": " "
                }
            ]
        },
        {
            "LogName": "Add gift tastes for Robin",
            "Action": "EditData",
            "Target": "Data/NPCGiftTastes",
            "TextOperations": [
                {
                    "Operation": "Append",
                    "Target": ["Fields", "Robin", 3],
                    "Value": "jams_and_pies_object",
                    "Delimiter": " "
                },
                {
                    "Operation": "Append",
                    "Target": ["Fields", "Robin", 1],
                    "Value": "{{ModId}}_PineapplePie {{ModId}}_StarfruitPie {{ModId}}_PineappleJam {{ModId}}_StarfruitJam",
                    "Delimiter": " "
                }
            ]
        },
        {
            "LogName": "Add gift tastes for Sam",
            "Action": "EditData",
            "Target": "Data/NPCGiftTastes",
            "TextOperations": [
                {
                    "Operation": "Append",
                    "Target": ["Fields", "Sam", 1],
                    "Value": "{{ModId}}_CactusFruitPie {{ModId}}_CactusFruitJam",
                    "Delimiter": " "
                }
            ]
        },
        {
            "LogName": "Add gift tastes for Sandy",
            "Action": "EditData",
            "Target": "Data/NPCGiftTastes",
            "TextOperations": [
                {
                    "Operation": "Append",
                    "Target": ["Fields", "Sandy", 3],
                    "Value": "jams_and_pies_object",
                    "Delimiter": " "
                },
                {
                    "Operation": "Append",
                    "Target": ["Fields", "Sandy", 1],
                    "Value": "{{ModId}}_MelonPie {{ModId}}_MelonJam",
                    "Delimiter": " "
                }
            ]
        },
        {
            "LogName": "Add gift tastes for Shane",
            "Action": "EditData",
            "Target": "Data/NPCGiftTastes",
            "TextOperations": [
                {
                    "Operation": "Append",
                    "Target": ["Fields", "Shane", 3],
                    "Value": "jams_and_pies_object",
                    "Delimiter": " "
                },
                {
                    "Operation": "Append",
                    "Target": ["Fields", "Shane", 1],
                    "Value": "{{ModId}}_BananaPie {{ModId}}_BlackberryPie {{ModId}}_BananaJam {{ModId}}_BlackberryJam",
                    "Delimiter": " "
                }
            ]
        },
        {
            "LogName": "Add gift tastes for Vincent",
            "Action": "EditData",
            "Target": "Data/NPCGiftTastes",
            "TextOperations": [
                {
                    "Operation": "Append",
                    "Target": ["Fields", "Vincent", 5],
                    "Value": "jams_and_pies_object",
                    "Delimiter": " "
                },
                {
                    "Operation": "Append",
                    "Target": ["Fields", "Vincent", 1],
                    "Value": "{{ModId}}_GrapePie {{ModId}}_GrapeJam",
                    "Delimiter": " "
                },
                {
                    "Operation": "Append",
                    "Target": ["Fields", "Vincent", 3],
                    "Value": "{{ModId}}_ApplePie {{ModId}}_ApricotPie {{ModId}}_CherryPie  {{ModId}}_CoconutPie {{ModId}}_OrangePie {{ModId}}_PeachPie {{ModId}}_PomegranatePie {{ModId}}_AppleJam {{ModId}}_ApricotJam {{ModId}}_CherryJam {{ModId}}_CoconutJam {{ModId}}_OrangeJam {{ModId}}_PeachJam {{ModId}}_PomegranateJam",
                    "Delimiter": " "
                },
                {
                    "Operation": "Append",
                    "Target": ["Fields", "Vincent", 9],
                    "Value": "{{ModId}}_SalmonberryPie {{ModId}}_SalmonberryJam",
                    "Delimiter": " "
                }
            ]
        },
        {
            "LogName": "Add gift tastes for Wizard",
            "Action": "EditData",
            "Target": "Data/NPCGiftTastes",
            "TextOperations": [
                {
                    "Operation": "Append",
                    "Target": ["Fields", "Wizard", 3],
                    "Value": "{{ModId}}_AncientFruitPie {{ModId}}_AncientFruitJam",
                    "Delimiter": " "
                }
            ]
        }
    ]
}