{
    "Changes": [
		{
        	"Action": "EditData",
        	"Target": "Data/Locations",
        	"TargetField": [ "Desert", "Forage" ],
        	"Entries": {
                "Strarfruitspawn": {
					"Chance": 0.1,
                	"ItemId": "268"
                }
        	}
        },
        {
        	"Action": "EditData",
        	"Target": "Data/Locations",
        	"TargetField": [ "Forest", "Forage" ],
        	"Entries": {
                "Timsanity_TimoDaisy": {
                	"ItemId": "(O)Timsanity_TimoDaisy",
                	"Condition": "SEASON spring fall",
					"Chance": 1.0,
                },
                "Timsanity_TimoDaisy2": {
                	"ItemId": "(O)Timsanity_TimoDaisy",
                	"Condition": "SEASON spring fall",
					"Chance": 1.0,
                },
                "Timsanity_TimoDaisy3": {
                	"ItemId": "(O)Timsanity_TimoDaisy",
                	"Condition": "SEASON spring fall",
					"Chance": 1.0,
                },
                "ancientfruit": {
                	"ItemId": "454",
                	"Condition": "SEASON spring summer fall",
					"Chance": 0.01,
                },
                "Horseradish": {
                	"ItemId": "16",
                	"Season": "spring",
					"Chance": 1.0,
                },
                "Daffodil": {
                	"ItemId": "18",
                	"Season": "spring",
					"Chance": 1.0,
                },
                "Leek": {
                	"ItemId": "20",
                	"Season": "spring",
					"Chance": 1.0,
                },
                "Dandelion": {
                	"ItemId": "22",
                	"Season": "spring",
					"Chance": 1.0,
                },
                "Morel": {
                	"ItemId": "257",
                	"Season": "spring",
					"Chance": 0.5,
                },
                "SpiceBerry": {
                	"ItemId": "396",
                	"Season": "summer",
					"Chance": 1.0,
                },
                "SweetPea": {
                	"ItemId": "398",
                	"Season": "summer",
					"Chance": 1.0,
                },
                "Grape": {
                	"ItemId": "402",
                	"Season": "summer",
					"Chance": 1.0,
                },
                "zinnia": {
                	"ItemId": "(O)Timsanity_RedZinnia",
                	"Season": "summer",
					"Chance": 1.0,
                },
                "FiddleheadFern": {
                	"ItemId": "259",
                	"Season": "summer",
					"Chance": 0.5,
                },
                "commonshroom": {
                	"ItemId": "404",
                	"Season": "fall",
					"Chance": 1.0,
                },
                "plum": {
                	"ItemId": "406",
                	"Season": "fall",
					"Chance": 1.0,
                },
                "hazel": {
                	"ItemId": "408",
                	"Season": "fall",
					"Chance": 1.0,
                },
                "blackberry": {
                	"ItemId": "410",
                	"Season": "fall",
					"Chance": 1.0,
                },
                "leaflump": {
                	"ItemId": "(O)Timsanity_LeafLump",
                	"Season": "fall",
					"Chance": 0.5,
                },
                "autumnoffering": {
                	"ItemId": "(O)Timsanity_AutumnOffering",
                	"Season": "fall",
					"Chance": 0.5,
                },
                "chant": {
                	"ItemId": "281",
                	"Season": "fall",
					"Chance": 0.6,
                },
                "redshroom": {
                	"ItemId": "420",
                	"Season": "fall",
					"Chance": 0.5,
                },
                "purpleshroom": {
                	"ItemId": "422",
                	"Season": "fall",
					"Chance": 0.25,
                },
                "truffle": {
                	"ItemId": "430",
                	"Season": "fall",
					"Chance": 0.1,
                },
                "FamousMushroom": {
                	"ItemId": "(O)Timsanity_FamousMushroom",
                	"Season": "fall",
					"Chance": 0.1,
                },
                "ElegantMushroom": {
                	"ItemId": "(O)Timsanity_ElegantMushroom",
                	"Season": "fall",
					"Chance": 0.15,
                },
                "RoundMushroom": {
                	"ItemId": "(O)Timsanity_RoundMushroom",
                	"Season": "fall",
					"Chance": 1.0,
                },
                "FlatMushroom": {
                	"ItemId": "(O)Timsanity_FlatMushroom",
                	"Season": "fall",
					"Chance": 0.9,
                },
                "SkinnyMushroom": {
                	"ItemId": "(O)Timsanity_SkinnyMushroom",
                	"Season": "fall",
					"Chance": 0.8,
                },
                "FallGinkgoLeaf": {
                	"ItemId": "(O)Timsanity_FallGinkgoLeaf",
                	"Season": "fall",
					"Chance": 0.55,
                },
                "PocketCampTruffle": {
                	"ItemId": "(O)Timsanity_PocketCampTruffle",
                	"Season": "fall",
					"Chance": 0.7,
                },
                "gemberry": {
                	"ItemId": "417",
                	"Season": "fall",
					"Chance": 0.01,
                },
                "winterroot": {
                	"ItemId": "412",
                	"Season": "winter",
					"Chance": 1.0,
                },
                "crystalfruit": {
                	"ItemId": "414",
                	"Season": "winter",
					"Chance": 1.0,
                },
                "snowyam": {
                	"ItemId": "416",
                	"Season": "winter",
					"Chance": 1.0,
                },
                "crocus": {
                	"ItemId": "418",
                	"Season": "winter",
					"Chance": 1.0,
                },
                "RedOrnament": {
                	"ItemId": "(O)Timsanity_RedOrnament",
                	"Season": "winter",
					"Chance": 1.0,
                },
                "GoldOrnament": {
                	"ItemId": "(O)Timsanity_GoldOrnament",
                	"Season": "winter",
					"Chance": 1.0,
                },
                "GreenOrnament": {
                	"ItemId": "(O)Timsanity_GreenOrnament",
                	"Season": "winter",
					"Chance": 1.0,
                },
                "BlueOrnament": {
                	"ItemId": "(O)Timsanity_BlueOrnament",
                	"Season": "winter",
					"Chance": 1.0,
                },
                "PoinsettiaOrnament": {
                	"ItemId": "(O)Timsanity_PoinsettiaOrnament",
                	"Season": "winter",
					"Chance": 0.35,
                },
                "BrownPineConeTree": {
                	"ItemId": "(O)Timsanity_BrownPineConeTree",
                	"Season": "winter",
					"Chance": 0.45,
                },
                "SilverPineConeTree": {
                	"ItemId": "(O)Timsanity_SilverPineConeTree",
                	"Season": "winter",
					"Chance": 0.15,
                },
                "holly": {
                	"ItemId": "283",
                	"Season": "winter",
					"Chance": 0.5,
                },
                "yellowcrocus": {
                	"ItemId": "(O)Timsanity_YellowCrocus",
                	"Season": "winter",
					"Chance": 0.5
                },
                "jinglebellholly": {
                	"ItemId": "(O)Timsanity_JingleBellHolly",
                	"Season": "winter",
					"Chance": 0.15
                },
        	}
        },
		{
        	"Action": "EditData",
        	"Target": "Data/Locations",
        	"TargetField": [ "BusStop", "Forage" ],
        	"Entries": {
                "Timsanity_TimoDaisy": {
                	"ItemId": "(O)Timsanity_TimoDaisy",
                	"Condition": "SEASON spring fall",
					"Chance": 1.0,
                },
                "Timsanity_TimoDaisy2": {
                	"ItemId": "(O)Timsanity_TimoDaisy",
                	"Condition": "SEASON spring fall",
					"Chance": 1.0,
                },
                "Timsanity_TimoDaisy3": {
                	"ItemId": "(O)Timsanity_TimoDaisy",
                	"Condition": "SEASON spring fall",
					"Chance": 1.0,
                },
                "ancientfruit": {
                	"ItemId": "454",
                	"Condition": "SEASON spring summer fall",
					"Chance": 0.01,
                },
                "Horseradish": {
                	"ItemId": "16",
                	"Season": "spring",
					"Chance": 1.0,
                },
                "Daffodil": {
                	"ItemId": "18",
                	"Season": "spring",
					"Chance": 1.0,
                },
                "Leek": {
                	"ItemId": "20",
                	"Season": "spring",
					"Chance": 1.0,
                },
                "Dandelion": {
                	"ItemId": "22",
                	"Season": "spring",
					"Chance": 1.0,
                },
                "Morel": {
                	"ItemId": "257",
                	"Season": "spring",
					"Chance": 0.5,
                },
                "SpiceBerry": {
                	"ItemId": "396",
                	"Season": "summer",
					"Chance": 1.0,
                },
                "SweetPea": {
                	"ItemId": "398",
                	"Season": "summer",
					"Chance": 1.0,
                },
                "Grape": {
                	"ItemId": "402",
                	"Season": "summer",
					"Chance": 1.0,
                },
                "zinnia": {
                	"ItemId": "(O)Timsanity_RedZinnia",
                	"Season": "summer",
					"Chance": 1.0,
                },
                "FiddleheadFern": {
                	"ItemId": "259",
                	"Season": "summer",
					"Chance": 0.5,
                },
                "commonshroom": {
                	"ItemId": "404",
                	"Season": "fall",
					"Chance": 1.0,
                },
                "plum": {
                	"ItemId": "406",
                	"Season": "fall",
					"Chance": 1.0,
                },
                "hazel": {
                	"ItemId": "408",
                	"Season": "fall",
					"Chance": 1.0,
                },
                "blackberry": {
                	"ItemId": "410",
                	"Season": "fall",
					"Chance": 1.0,
                },
                "leaflump": {
                	"ItemId": "(O)Timsanity_LeafLump",
                	"Season": "fall",
					"Chance": 0.5,
                },
                "autumnoffering": {
                	"ItemId": "(O)Timsanity_AutumnOffering",
                	"Season": "fall",
					"Chance": 0.5,
                },
                "chant": {
                	"ItemId": "281",
                	"Season": "fall",
					"Chance": 0.6,
                },
                "redshroom": {
                	"ItemId": "420",
                	"Season": "fall",
					"Chance": 0.5,
                },
                "purpleshroom": {
                	"ItemId": "422",
                	"Season": "fall",
					"Chance": 0.25,
                },
                "truffle": {
                	"ItemId": "430",
                	"Season": "fall",
					"Chance": 0.1,
                },
                "FamousMushroom": {
                	"ItemId": "(O)Timsanity_FamousMushroom",
                	"Season": "fall",
					"Chance": 0.1,
                },
                "ElegantMushroom": {
                	"ItemId": "(O)Timsanity_ElegantMushroom",
                	"Season": "fall",
					"Chance": 0.15,
                },
                "RoundMushroom": {
                	"ItemId": "(O)Timsanity_RoundMushroom",
                	"Season": "fall",
					"Chance": 1.0,
                },
                "FlatMushroom": {
                	"ItemId": "(O)Timsanity_FlatMushroom",
                	"Season": "fall",
					"Chance": 0.9,
                },
                "SkinnyMushroom": {
                	"ItemId": "(O)Timsanity_SkinnyMushroom",
                	"Season": "fall",
					"Chance": 0.8,
                },
                "FallGinkgoLeaf": {
                	"ItemId": "(O)Timsanity_FallGinkgoLeaf",
                	"Season": "fall",
					"Chance": 0.55,
                },
                "PocketCampTruffle": {
                	"ItemId": "(O)Timsanity_PocketCampTruffle",
                	"Season": "fall",
					"Chance": 0.7,
                },
                "gemberry": {
                	"ItemId": "417",
                	"Season": "fall",
					"Chance": 0.01,
                },
                "winterroot": {
                	"ItemId": "412",
                	"Season": "winter",
					"Chance": 1.0,
                },
                "crystalfruit": {
                	"ItemId": "414",
                	"Season": "winter",
					"Chance": 1.0,
                },
                "snowyam": {
                	"ItemId": "416",
                	"Season": "winter",
					"Chance": 1.0,
                },
                "crocus": {
                	"ItemId": "418",
                	"Season": "winter",
					"Chance": 1.0,
                },
                "RedOrnament": {
                	"ItemId": "(O)Timsanity_RedOrnament",
                	"Season": "winter",
					"Chance": 1.0,
                },
                "GoldOrnament": {
                	"ItemId": "(O)Timsanity_GoldOrnament",
                	"Season": "winter",
					"Chance": 1.0,
                },
                "GreenOrnament": {
                	"ItemId": "(O)Timsanity_GreenOrnament",
                	"Season": "winter",
					"Chance": 1.0,
                },
                "BlueOrnament": {
                	"ItemId": "(O)Timsanity_BlueOrnament",
                	"Season": "winter",
					"Chance": 1.0,
                },
                "PoinsettiaOrnament": {
                	"ItemId": "(O)Timsanity_PoinsettiaOrnament",
                	"Season": "winter",
					"Chance": 0.35,
                },
                "BrownPineConeTree": {
                	"ItemId": "(O)Timsanity_BrownPineConeTree",
                	"Season": "winter",
					"Chance": 0.45,
                },
                "SilverPineConeTree": {
                	"ItemId": "(O)Timsanity_SilverPineConeTree",
                	"Season": "winter",
					"Chance": 0.15,
                },
                "holly": {
                	"ItemId": "283",
                	"Season": "winter",
					"Chance": 0.5,
                },
                "yellowcrocus": {
                	"ItemId": "(O)Timsanity_YellowCrocus",
                	"Season": "winter",
					"Chance": 0.5
                },
                "jinglebellholly": {
                	"ItemId": "(O)Timsanity_JingleBellHolly",
                	"Season": "winter",
					"Chance": 0.15
                },
        	}
        },
		{
        	"Action": "EditData",
        	"Target": "Data/Locations",
        	"TargetField": [ "Town", "Forage" ],
        	"Entries": {
                "Timsanity_TimoDaisy": {
                	"ItemId": "(O)Timsanity_TimoDaisy",
                	"Condition": "SEASON spring fall",
					"Chance": 1.0,
                },
                "Timsanity_TimoDaisy2": {
                	"ItemId": "(O)Timsanity_TimoDaisy",
                	"Condition": "SEASON spring fall",
					"Chance": 1.0,
                },
                "Timsanity_TimoDaisy3": {
                	"ItemId": "(O)Timsanity_TimoDaisy",
                	"Condition": "SEASON spring fall",
					"Chance": 1.0,
                },
                "ancientfruit": {
                	"ItemId": "454",
                	"Condition": "SEASON spring summer fall",
					"Chance": 0.01,
                },
                "Horseradish": {
                	"ItemId": "16",
                	"Season": "spring",
					"Chance": 1.0,
                },
                "Daffodil": {
                	"ItemId": "18",
                	"Season": "spring",
					"Chance": 1.0,
                },
                "Leek": {
                	"ItemId": "20",
                	"Season": "spring",
					"Chance": 1.0,
                },
                "Dandelion": {
                	"ItemId": "22",
                	"Season": "spring",
					"Chance": 1.0,
                },
                "Morel": {
                	"ItemId": "257",
                	"Season": "spring",
					"Chance": 0.5,
                },
                "SpiceBerry": {
                	"ItemId": "396",
                	"Season": "summer",
					"Chance": 1.0,
                },
                "SweetPea": {
                	"ItemId": "398",
                	"Season": "summer",
					"Chance": 1.0,
                },
                "Grape": {
                	"ItemId": "402",
                	"Season": "summer",
					"Chance": 1.0,
                },
                "zinnia": {
                	"ItemId": "(O)Timsanity_RedZinnia",
                	"Season": "summer",
					"Chance": 1.0,
                },
                "FiddleheadFern": {
                	"ItemId": "259",
                	"Season": "summer",
					"Chance": 0.5,
                },
                "commonshroom": {
                	"ItemId": "404",
                	"Season": "fall",
					"Chance": 1.0,
                },
                "plum": {
                	"ItemId": "406",
                	"Season": "fall",
					"Chance": 1.0,
                },
                "hazel": {
                	"ItemId": "408",
                	"Season": "fall",
					"Chance": 1.0,
                },
                "blackberry": {
                	"ItemId": "410",
                	"Season": "fall",
					"Chance": 1.0,
                },
                "leaflump": {
                	"ItemId": "(O)Timsanity_LeafLump",
                	"Season": "fall",
					"Chance": 0.5,
                },
                "autumnoffering": {
                	"ItemId": "(O)Timsanity_AutumnOffering",
                	"Season": "fall",
					"Chance": 0.5,
                },
                "chant": {
                	"ItemId": "281",
                	"Season": "fall",
					"Chance": 0.6,
                },
                "redshroom": {
                	"ItemId": "420",
                	"Season": "fall",
					"Chance": 0.5,
                },
                "purpleshroom": {
                	"ItemId": "422",
                	"Season": "fall",
					"Chance": 0.25,
                },
                "truffle": {
                	"ItemId": "430",
                	"Season": "fall",
					"Chance": 0.1,
                },
                "FamousMushroom": {
                	"ItemId": "(O)Timsanity_FamousMushroom",
                	"Season": "fall",
					"Chance": 0.1,
                },
                "ElegantMushroom": {
                	"ItemId": "(O)Timsanity_ElegantMushroom",
                	"Season": "fall",
					"Chance": 0.15,
                },
                "RoundMushroom": {
                	"ItemId": "(O)Timsanity_RoundMushroom",
                	"Season": "fall",
					"Chance": 1.0,
                },
                "FlatMushroom": {
                	"ItemId": "(O)Timsanity_FlatMushroom",
                	"Season": "fall",
					"Chance": 0.9,
                },
                "SkinnyMushroom": {
                	"ItemId": "(O)Timsanity_SkinnyMushroom",
                	"Season": "fall",
					"Chance": 0.8,
                },
                "FallGinkgoLeaf": {
                	"ItemId": "(O)Timsanity_FallGinkgoLeaf",
                	"Season": "fall",
					"Chance": 0.55,
                },
                "PocketCampTruffle": {
                	"ItemId": "(O)Timsanity_PocketCampTruffle",
                	"Season": "fall",
					"Chance": 0.7,
                },
                "gemberry": {
                	"ItemId": "417",
                	"Season": "fall",
					"Chance": 0.01,
                },
                "winterroot": {
                	"ItemId": "412",
                	"Season": "winter",
					"Chance": 1.0,
                },
                "crystalfruit": {
                	"ItemId": "414",
                	"Season": "winter",
					"Chance": 1.0,
                },
                "snowyam": {
                	"ItemId": "416",
                	"Season": "winter",
					"Chance": 1.0,
                },
                "crocus": {
                	"ItemId": "418",
                	"Season": "winter",
					"Chance": 1.0,
                },
                "RedOrnament": {
                	"ItemId": "(O)Timsanity_RedOrnament",
                	"Season": "winter",
					"Chance": 1.0,
                },
                "GoldOrnament": {
                	"ItemId": "(O)Timsanity_GoldOrnament",
                	"Season": "winter",
					"Chance": 1.0,
                },
                "GreenOrnament": {
                	"ItemId": "(O)Timsanity_GreenOrnament",
                	"Season": "winter",
					"Chance": 1.0,
                },
                "BlueOrnament": {
                	"ItemId": "(O)Timsanity_BlueOrnament",
                	"Season": "winter",
					"Chance": 1.0,
                },
                "PoinsettiaOrnament": {
                	"ItemId": "(O)Timsanity_PoinsettiaOrnament",
                	"Season": "winter",
					"Chance": 0.35,
                },
                "BrownPineConeTree": {
                	"ItemId": "(O)Timsanity_BrownPineConeTree",
                	"Season": "winter",
					"Chance": 0.45,
                },
                "SilverPineConeTree": {
                	"ItemId": "(O)Timsanity_SilverPineConeTree",
                	"Season": "winter",
					"Chance": 0.15,
                },
                "holly": {
                	"ItemId": "283",
                	"Season": "winter",
					"Chance": 0.5,
                },
                "yellowcrocus": {
                	"ItemId": "(O)Timsanity_YellowCrocus",
                	"Season": "winter",
					"Chance": 0.5
                },
                "jinglebellholly": {
                	"ItemId": "(O)Timsanity_JingleBellHolly",
                	"Season": "winter",
					"Chance": 0.15
                },
        	}
        },
		{
        	"Action": "EditData",
        	"Target": "Data/Locations",
        	"TargetField": [ "Mountain", "Forage" ],
        	"Entries": {
                "Timsanity_TimoDaisy": {
                	"ItemId": "(O)Timsanity_TimoDaisy",
                	"Condition": "SEASON spring fall",
					"Chance": 1.0,
                },
                "Timsanity_TimoDaisy2": {
                	"ItemId": "(O)Timsanity_TimoDaisy",
                	"Condition": "SEASON spring fall",
					"Chance": 1.0,
                },
                "Timsanity_TimoDaisy3": {
                	"ItemId": "(O)Timsanity_TimoDaisy",
                	"Condition": "SEASON spring fall",
					"Chance": 1.0,
                },
                "ancientfruit": {
                	"ItemId": "454",
                	"Condition": "SEASON spring summer fall",
					"Chance": 0.01,
                },
                "Horseradish": {
                	"ItemId": "16",
                	"Season": "spring",
					"Chance": 1.0,
                },
                "Daffodil": {
                	"ItemId": "18",
                	"Season": "spring",
					"Chance": 1.0,
                },
                "Leek": {
                	"ItemId": "20",
                	"Season": "spring",
					"Chance": 1.0,
                },
                "Dandelion": {
                	"ItemId": "22",
                	"Season": "spring",
					"Chance": 1.0,
                },
                "Morel": {
                	"ItemId": "257",
                	"Season": "spring",
					"Chance": 0.5,
                },
                "SpiceBerry": {
                	"ItemId": "396",
                	"Season": "summer",
					"Chance": 1.0,
                },
                "SweetPea": {
                	"ItemId": "398",
                	"Season": "summer",
					"Chance": 1.0,
                },
                "Grape": {
                	"ItemId": "402",
                	"Season": "summer",
					"Chance": 1.0,
                },
                "zinnia": {
                	"ItemId": "(O)Timsanity_RedZinnia",
                	"Season": "summer",
					"Chance": 1.0,
                },
                "FiddleheadFern": {
                	"ItemId": "259",
                	"Season": "summer",
					"Chance": 0.5,
                },
                "commonshroom": {
                	"ItemId": "404",
                	"Season": "fall",
					"Chance": 1.0,
                },
                "plum": {
                	"ItemId": "406",
                	"Season": "fall",
					"Chance": 1.0,
                },
                "hazel": {
                	"ItemId": "408",
                	"Season": "fall",
					"Chance": 1.0,
                },
                "blackberry": {
                	"ItemId": "410",
                	"Season": "fall",
					"Chance": 1.0,
                },
                "leaflump": {
                	"ItemId": "(O)Timsanity_LeafLump",
                	"Season": "fall",
					"Chance": 0.5,
                },
                "autumnoffering": {
                	"ItemId": "(O)Timsanity_AutumnOffering",
                	"Season": "fall",
					"Chance": 0.5,
                },
                "chant": {
                	"ItemId": "281",
                	"Season": "fall",
					"Chance": 0.6,
                },
                "redshroom": {
                	"ItemId": "420",
                	"Season": "fall",
					"Chance": 0.5,
                },
                "purpleshroom": {
                	"ItemId": "422",
                	"Season": "fall",
					"Chance": 0.25,
                },
                "truffle": {
                	"ItemId": "430",
                	"Season": "fall",
					"Chance": 0.1,
                },
                "FamousMushroom": {
                	"ItemId": "(O)Timsanity_FamousMushroom",
                	"Season": "fall",
					"Chance": 0.1,
                },
                "ElegantMushroom": {
                	"ItemId": "(O)Timsanity_ElegantMushroom",
                	"Season": "fall",
					"Chance": 0.15,
                },
                "RoundMushroom": {
                	"ItemId": "(O)Timsanity_RoundMushroom",
                	"Season": "fall",
					"Chance": 1.0,
                },
                "FlatMushroom": {
                	"ItemId": "(O)Timsanity_FlatMushroom",
                	"Season": "fall",
					"Chance": 0.9,
                },
                "SkinnyMushroom": {
                	"ItemId": "(O)Timsanity_SkinnyMushroom",
                	"Season": "fall",
					"Chance": 0.8,
                },
                "FallGinkgoLeaf": {
                	"ItemId": "(O)Timsanity_FallGinkgoLeaf",
                	"Season": "fall",
					"Chance": 0.55,
                },
                "PocketCampTruffle": {
                	"ItemId": "(O)Timsanity_PocketCampTruffle",
                	"Season": "fall",
					"Chance": 0.7,
                },
                "gemberry": {
                	"ItemId": "417",
                	"Season": "fall",
					"Chance": 0.01,
                },
                "winterroot": {
                	"ItemId": "412",
                	"Season": "winter",
					"Chance": 1.0,
                },
                "crystalfruit": {
                	"ItemId": "414",
                	"Season": "winter",
					"Chance": 1.0,
                },
                "snowyam": {
                	"ItemId": "416",
                	"Season": "winter",
					"Chance": 1.0,
                },
                "crocus": {
                	"ItemId": "418",
                	"Season": "winter",
					"Chance": 1.0,
                },
                "RedOrnament": {
                	"ItemId": "(O)Timsanity_RedOrnament",
                	"Season": "winter",
					"Chance": 1.0,
                },
                "GoldOrnament": {
                	"ItemId": "(O)Timsanity_GoldOrnament",
                	"Season": "winter",
					"Chance": 1.0,
                },
                "GreenOrnament": {
                	"ItemId": "(O)Timsanity_GreenOrnament",
                	"Season": "winter",
					"Chance": 1.0,
                },
                "BlueOrnament": {
                	"ItemId": "(O)Timsanity_BlueOrnament",
                	"Season": "winter",
					"Chance": 1.0,
                },
                "PoinsettiaOrnament": {
                	"ItemId": "(O)Timsanity_PoinsettiaOrnament",
                	"Season": "winter",
					"Chance": 0.35,
                },
                "BrownPineConeTree": {
                	"ItemId": "(O)Timsanity_BrownPineConeTree",
                	"Season": "winter",
					"Chance": 0.45,
                },
                "SilverPineConeTree": {
                	"ItemId": "(O)Timsanity_SilverPineConeTree",
                	"Season": "winter",
					"Chance": 0.15,
                },
                "holly": {
                	"ItemId": "283",
                	"Season": "winter",
					"Chance": 0.5,
                },
                "yellowcrocus": {
                	"ItemId": "(O)Timsanity_YellowCrocus",
                	"Season": "winter",
					"Chance": 0.5
                },
                "jinglebellholly": {
                	"ItemId": "(O)Timsanity_JingleBellHolly",
                	"Season": "winter",
					"Chance": 0.15
                },
        	}
        },
		{
        	"Action": "EditData",
        	"Target": "Data/Locations",
        	"TargetField": [ "IslandWest", "Forage" ],
        	"Entries": {
                "Timsanity_RedHibiscus": {
                	"ItemId": "(O)Timsanity_RedHibiscus",
					"Chance": 1.0,
                },
                "Timsanity_RedHibiscus2": {
                	"ItemId": "(O)Timsanity_RedHibiscus",
					"Chance": 0.5,
                },
                "ginger": {
                	"ItemId": "829",
					"Chance": 1.0,
                },
                "Timsanity_RedHibiscus": {
                	"ItemId": "(O)Timsanity_OrangeHibiscus",
					"Chance": 0.5,
                },
                "Timsanity_RedIslandHibiscus": {
                	"ItemId": "(O)Timsanity_RedIslandHibiscus",
					"Chance": 0.25,
                },
                "Timsanity_YellowIslandHibiscus": {
                	"ItemId": "(O)Timsanity_YellowIslandHibiscus",
					"Chance": 0.125,
                },
                "Timsanity_WhitePlumeria": {
                	"ItemId": "(O)Timsanity_WhitePlumeria",
					"Chance": 0.75,
                },
                "Timsanity_YellowPlumeria": {
                	"ItemId": "(O)Timsanity_YellowPlumeria",
					"Chance": 0.5,
                },
                "Timsanity_RedPlumeria": {
                	"ItemId": "(O)Timsanity_RedPlumeria",
					"Chance": 0.25,
                },
                "Timsanity_RoundMushroom": {
                	"ItemId": "(O)Timsanity_RoundMushroom",
					"Chance": 0.25,
                },
                "Timsanity_WhitePoinsettia": {
                	"ItemId": "(O)Timsanity_WhitePoinsettia",
					"Chance": 0.1,
                },
                "Timsanity_RedPoinsettia": {
                	"ItemId": "(O)Timsanity_RedPoinsettia",
					"Chance": 0.1,
                },
                "Timsanity_BluePoinsettia": {
                	"ItemId": "(O)Timsanity_BluePoinsettia",
					"Chance": 0.1,
                },
                "Timsanity_ArcaneGreenSeaweed": {
                	"ItemId": "(O)Timsanity_ArcaneGreenSeaweed",
					"Chance": 0.5,
                },
                "Timsanity_ArcanePinkSeaweed": {
                	"ItemId": "(O)Timsanity_ArcanePinkSeaweed",
					"Chance": 0.25,
                },
                "Timsanity_BlueFantasyFlower": {
                	"ItemId": "(O)Timsanity_BlueFantasyFlower",
					"Chance": 0.15,
                },
                "Timsanity_YellowFantasyFlower": {
                	"ItemId": "(O)Timsanity_YellowFantasyFlower",
					"Chance": 0.05,
                },
                "Timsanity_BlitzClam": {
                	"ItemId": "(O)Timsanity_BlitzClam",
					"Chance": 1.0,
                },
                "coconut": {
                	"ItemId": "88",
					"Chance": 1.0,
                },
        	}
        },
		{
        	"Action": "EditData",
        	"Target": "Data/Locations",
        	"TargetField": [ "IslandEast", "Forage" ],
        	"Entries": {
                "Timsanity_RedHibiscus": {
                	"ItemId": "(O)Timsanity_RedHibiscus",
					"Chance": 1.0,
                },
                "Timsanity_RedHibiscus2": {
                	"ItemId": "(O)Timsanity_RedHibiscus",
					"Chance": 0.5,
                },
                "ginger": {
                	"ItemId": "829",
					"Chance": 1.0,
                },
                "Timsanity_RedHibiscus": {
                	"ItemId": "(O)Timsanity_OrangeHibiscus",
					"Chance": 0.5,
                },
                "Timsanity_RedIslandHibiscus": {
                	"ItemId": "(O)Timsanity_RedIslandHibiscus",
					"Chance": 0.25,
                },
                "Timsanity_YellowIslandHibiscus": {
                	"ItemId": "(O)Timsanity_YellowIslandHibiscus",
					"Chance": 0.125,
                },
                "Timsanity_WhitePlumeria": {
                	"ItemId": "(O)Timsanity_WhitePlumeria",
					"Chance": 0.75,
                },
                "Timsanity_YellowPlumeria": {
                	"ItemId": "(O)Timsanity_YellowPlumeria",
					"Chance": 0.5,
                },
                "Timsanity_RedPlumeria": {
                	"ItemId": "(O)Timsanity_RedPlumeria",
					"Chance": 0.25,
                },
                "Timsanity_RoundMushroom": {
                	"ItemId": "(O)Timsanity_RoundMushroom",
					"Chance": 0.25,
                },
                "Timsanity_WhitePoinsettia": {
                	"ItemId": "(O)Timsanity_WhitePoinsettia",
					"Chance": 0.1,
                },
                "Timsanity_RedPoinsettia": {
                	"ItemId": "(O)Timsanity_RedPoinsettia",
					"Chance": 0.1,
                },
                "Timsanity_BluePoinsettia": {
                	"ItemId": "(O)Timsanity_BluePoinsettia",
					"Chance": 0.1,
                },
                "Timsanity_ArcaneGreenSeaweed": {
                	"ItemId": "(O)Timsanity_ArcaneGreenSeaweed",
					"Chance": 0.5,
                },
                "Timsanity_ArcanePinkSeaweed": {
                	"ItemId": "(O)Timsanity_ArcanePinkSeaweed",
					"Chance": 0.25,
                },
                "Timsanity_BlueFantasyFlower": {
                	"ItemId": "(O)Timsanity_BlueFantasyFlower",
					"Chance": 0.15,
                },
                "Timsanity_YellowFantasyFlower": {
                	"ItemId": "(O)Timsanity_YellowFantasyFlower",
					"Chance": 0.05,
                },
                "Timsanity_BlitzClam": {
                	"ItemId": "(O)Timsanity_BlitzClam",
					"Chance": 1.0,
                },
                "coconut": {
                	"ItemId": "88",
					"Chance": 1.0,
                },
        	}
        },
		{
        	"Action": "EditData",
        	"Target": "Data/Locations",
        	"TargetField": [ "IslandNorth", "Forage" ],
        	"Entries": {
                "Timsanity_RedHibiscus": {
                	"ItemId": "(O)Timsanity_RedHibiscus",
					"Chance": 1.0,
                },
                "Timsanity_RedHibiscus2": {
                	"ItemId": "(O)Timsanity_RedHibiscus",
					"Chance": 0.5,
                },
                "ginger": {
                	"ItemId": "829",
					"Chance": 1.0,
                },
                "Timsanity_RedHibiscus": {
                	"ItemId": "(O)Timsanity_OrangeHibiscus",
					"Chance": 0.5,
                },
                "Timsanity_RedIslandHibiscus": {
                	"ItemId": "(O)Timsanity_RedIslandHibiscus",
					"Chance": 0.25,
                },
                "Timsanity_YellowIslandHibiscus": {
                	"ItemId": "(O)Timsanity_YellowIslandHibiscus",
					"Chance": 0.125,
                },
                "Timsanity_WhitePlumeria": {
                	"ItemId": "(O)Timsanity_WhitePlumeria",
					"Chance": 0.75,
                },
                "Timsanity_YellowPlumeria": {
                	"ItemId": "(O)Timsanity_YellowPlumeria",
					"Chance": 0.5,
                },
                "Timsanity_RedPlumeria": {
                	"ItemId": "(O)Timsanity_RedPlumeria",
					"Chance": 0.25,
                },
                "Timsanity_RoundMushroom": {
                	"ItemId": "(O)Timsanity_RoundMushroom",
					"Chance": 0.25,
                },
                "Timsanity_WhitePoinsettia": {
                	"ItemId": "(O)Timsanity_WhitePoinsettia",
					"Chance": 0.1,
                },
                "Timsanity_RedPoinsettia": {
                	"ItemId": "(O)Timsanity_RedPoinsettia",
					"Chance": 0.1,
                },
                "Timsanity_BluePoinsettia": {
                	"ItemId": "(O)Timsanity_BluePoinsettia",
					"Chance": 0.1,
                },
                "Timsanity_ArcaneGreenSeaweed": {
                	"ItemId": "(O)Timsanity_ArcaneGreenSeaweed",
					"Chance": 0.5,
                },
                "Timsanity_ArcanePinkSeaweed": {
                	"ItemId": "(O)Timsanity_ArcanePinkSeaweed",
					"Chance": 0.25,
                },
                "Timsanity_BlueFantasyFlower": {
                	"ItemId": "(O)Timsanity_BlueFantasyFlower",
					"Chance": 0.15,
                },
                "Timsanity_YellowFantasyFlower": {
                	"ItemId": "(O)Timsanity_YellowFantasyFlower",
					"Chance": 0.05,
                },
                "Timsanity_BlitzClam": {
                	"ItemId": "(O)Timsanity_BlitzClam",
					"Chance": 1.0,
                },
                "coconut": {
                	"ItemId": "88",
					"Chance": 1.0,
                },
        	}
        },
		{
        	"Action": "EditData",
        	"Target": "Data/Locations",
        	"TargetField": [ "IslandSouth", "Forage" ],
        	"Entries": {
                "Timsanity_RedHibiscus": {
                	"ItemId": "(O)Timsanity_RedHibiscus",
					"Chance": 0.1,
                },
                "Timsanity_RedHibiscus2": {
                	"ItemId": "(O)Timsanity_RedHibiscus",
					"Chance": 0.05,
                },
                "coconut": {
                	"ItemId": "88",
					"Chance": 1.0,
                },
                "ginger": {
                	"ItemId": "829",
					"Chance": 0.1,
                },
                "Timsanity_RedHibiscus": {
                	"ItemId": "(O)Timsanity_OrangeHibiscus",
					"Chance": 0.05,
                },
                "Timsanity_RedIslandHibiscus": {
                	"ItemId": "(O)Timsanity_RedIslandHibiscus",
					"Chance": 0.025,
                },
                "Timsanity_YellowIslandHibiscus": {
                	"ItemId": "(O)Timsanity_YellowIslandHibiscus",
					"Chance": 0.0125,
                },
                "Timsanity_WhitePlumeria": {
                	"ItemId": "(O)Timsanity_WhitePlumeria",
					"Chance": 0.075,
                },
                "Timsanity_YellowPlumeria": {
                	"ItemId": "(O)Timsanity_YellowPlumeria",
					"Chance": 0.05,
                },
                "Timsanity_RedPlumeria": {
                	"ItemId": "(O)Timsanity_RedPlumeria",
					"Chance": 0.025,
                },
                "Timsanity_RoundMushroom": {
                	"ItemId": "(O)Timsanity_RoundMushroom",
					"Chance": 0.025,
                },
                "Timsanity_WhitePoinsettia": {
                	"ItemId": "(O)Timsanity_WhitePoinsettia",
					"Chance": 0.01,
                },
                "Timsanity_RedPoinsettia": {
                	"ItemId": "(O)Timsanity_RedPoinsettia",
					"Chance": 0.01,
                },
                "Timsanity_BluePoinsettia": {
                	"ItemId": "(O)Timsanity_BluePoinsettia",
					"Chance": 0.01,
                },
                "Timsanity_ArcaneGreenSeaweed": {
                	"ItemId": "(O)Timsanity_ArcaneGreenSeaweed",
					"Chance": 0.05,
                },
                "Timsanity_ArcanePinkSeaweed": {
                	"ItemId": "(O)Timsanity_ArcanePinkSeaweed",
					"Chance": 0.025,
                },
                "Timsanity_BlueFantasyFlower": {
                	"ItemId": "(O)Timsanity_BlueFantasyFlower",
					"Chance": 0.015,
                },
                "Timsanity_YellowFantasyFlower": {
                	"ItemId": "(O)Timsanity_YellowFantasyFlower",
					"Chance": 0.005,
                },
                "Timsanity_BlitzClam": {
                	"ItemId": "(O)Timsanity_BlitzClam",
					"Chance": 0.1,
                },
        	}
        },
    ]
}