{
	"Changes": [
		{
			"Action": "EditData",
			"Target": "Data/CraftingRecipes",
			"Entries": {
				"B.DDCP_TrashSeeds": "168 5 770 5/Field/B.DDCP_TrashSeeds 1/false/Foraging 10",
				"B.DDCP_SilverParsnipSeeds": "472 1 335 1/Field/B.DDCP_SilverParsnipSeeds 1/false/Farming 5",
				"B.DDCP_GigaParsnipSeeds": "472 10/Field/B.DDCP_GigaParsnipSeeds 1/false/Farming 5",
				"B.DDCP_StrangePeaSeeds": "473 1 768 10/Field/B.DDCP_StrangePeaSeeds 1/false/Farming 2",
				"B.DDCP_StrangeWarmPeaSeeds": "482 1 768 15/Field/B.DDCP_StrangeWarmPeaSeeds 1/false/Farming 5",
				"B.DDCP_StrangeColdPeaSeeds": "414 1 768 12/Field/B.DDCP_StrangeColdPeaSeeds 1/false/Farming 5",
				"B.DDCP_StrangeSpookyPeaSeeds": "301 1 768 17/Field/B.DDCP_StrangeSpookyPeaSeeds 1/false/Farming 5",
				"B.DDCP_StrangeGlowingSpookyPeaSeeds": "B.DDCP_StrangeSpookyPeaSeeds 1 769 20/Field/B.DDCP_StrangeGlowingSpookyPeaSeeds 1/false/Farming 8",
				"B.DDCP_JungleSpores": "92 10 259 1 338 1/Field/B.DDCP_JungleSpores 5/false/Foraging 7",
				"B.DDCP_DryadPumpkinSeeds": "773 1 490 10/Field/B.DDCP_DryadPumpkinSeeds 10/false/Combat 2",
				"B.DDCP_StrangeSunflowerSeeds": "431 1 768 5/Field/B.DDCP_StrangeSunflowerSeeds 1/false/Combat 5",
			}
		}
		
	]
}