{

  "Changes": [
      {
          "Action": "Load",
          "Target": "Maps/MrMrRogers.EchoReef_MaeHouse",
          "FromFile": "assets/Locations/EchoReef_MaeHouse.tmx"
      },
      {
          "Action": "Load",
          "Target": "Maps/MrMrRogers.EchoReef_MaeTheatre",
          "FromFile": "assets/Locations/EchoReef_MaeTheatre.tmx"
      },
      {
        "Action": "Load",
        "Target": "Characters/MrMrRogers.EchoReef_Mae",
        "FromFile": "assets/Sprites/Mae.png"
      },
      {
        "Action": "Load",
        "Target": "Portraits/MrMrRogers.EchoReef_Mae",
        "FromFile": "assets/Portraits/Mae.png"
      },
      {
          "Action": "EditData",
          "Target": "Data/Locations",
          "Entries": {
              "MrMrRogers.EchoReef_MaeHouse": {
                  "DisplayName": "{{i18n:MaeHouse}}",
                  "DefaultArrivalTile": {
                    "X": 8,
                    "Y": 10
                  },
                  "ExcludeFromNpcPathfinding": false,
                  "CreateOnLoad": {
                    "MapPath": "Maps/MrMrRogers.EchoReef_MaeHouse",
                    "Type": null,
                    "AlwaysActive": false
                  },
                  "FormerLocationNames": [],
                  "CanPlantHere": null,
                  "CanHaveGreenRainSpawns": true,
                  "ArtifactSpots": [],
                  "FishAreas": {},
                  "Fish": [],
                  "Forage": [],
                  "MinDailyWeeds": 2,
                  "MaxDailyWeeds": 5,
                  "FirstDayWeedMultiplier": 15,
                  "MinDailyForageSpawn": 1,
                  "MaxDailyForageSpawn": 4,
                  "MaxSpawnedForageAtOnce": 6,
                  "ChanceForClay": 0.03,
                  "Music": [],
                  "MusicDefault": null,
                  "MusicContext": "Default",
                  "MusicIgnoredInRain": false,
                  "MusicIgnoredInSpring": false,
                  "MusicIgnoredInSummer": false,
                  "MusicIgnoredInFall": false,
                  "MusicIgnoredInFallDebris": false,
                  "MusicIgnoredInWinter": false,
                  "MusicIsTownTheme": false,
                  "CustomFields": null
              },
              "MrMrRogers.EchoReef_MaeTheatre": {
                  "DisplayName": "{{i18n:MaeTheatre}}",
                  "DefaultArrivalTile": {
                    "X": 9,
                    "Y": 29
                  },
                  "ExcludeFromNpcPathfinding": false,
                  "CreateOnLoad": {
                    "MapPath": "Maps/MrMrRogers.EchoReef_MaeTheatre",
                    "Type": null,
                    "AlwaysActive": false
                  },
                  "FormerLocationNames": [],
                  "CanPlantHere": null,
                  "CanHaveGreenRainSpawns": true,
                  "ArtifactSpots": [],
                  "FishAreas": {},
                  "Fish": [],
                  "Forage": [],
                  "MinDailyWeeds": 2,
                  "MaxDailyWeeds": 5,
                  "FirstDayWeedMultiplier": 15,
                  "MinDailyForageSpawn": 1,
                  "MaxDailyForageSpawn": 4,
                  "MaxSpawnedForageAtOnce": 6,
                  "ChanceForClay": 0.03,
                  "Music": [],
                  "MusicDefault": null,
                  "MusicContext": "Default",
                  "MusicIgnoredInRain": false,
                  "MusicIgnoredInSpring": false,
                  "MusicIgnoredInSummer": false,
                  "MusicIgnoredInFall": false,
                  "MusicIgnoredInFallDebris": false,
                  "MusicIgnoredInWinter": false,
                  "MusicIsTownTheme": false,
                  "CustomFields": null
              }
          }
      },
      {
        "Action": "EditMap",
        "Target": "Maps/MrMrRogers.EchoReef_MaeHouse",
        "MapProperties": {
          "LocationContext": "EchoReef",
          "Warp": "8 11 MrMrRogers.EchoReef_Graveyard 30 50"
        }
      },
      {
        "Action": "EditMap",
        "Target": "Maps/MrMrRogers.EchoReef_Arena",
        "MapTiles":[
          {
            "Position": { 
              "X": 18, 
              "Y": 7
            },
            "Layer": "Buildings",
            "SetProperties": {
              "Action": "OpenShop MrMrRogers.EchoReef_FightShop down 0800 2000 18 6 1 1"
            }
          }
        ]
      },
      {
        "Action": "EditMap",
        "Target": "Maps/MrMrRogers.EchoReef_Graveyard",
        "MapTiles":[
          {
            "Position": { 
              "X": 30, 
              "Y": 49
            },
            "Layer": "Buildings",
            "SetProperties": {
              "Action": "LockedDoorWarp 8 10 MrMrRogers.EchoReef_MaeHouse 800 2000"
            }
          }
        ]
      },
      {
        "Action": "EditMap",
        "Target": "Maps/MrMrRogers.EchoReef_Graveyard",
        "MapTiles":[
          {
            "Position": { 
              "X": 41, 
              "Y": 19
            },
            "Layer": "Buildings",
            "SetProperties": {
              "Action": "Warp 9 29 MrMrRogers.EchoReef_MaeTheatre"
            }
          }
        ],
        "When": {
          "Hearts:MrMrRogers.EchoReef_Mae": "6"
        }
      },
      {
        "Action": "EditMap",
        "Target": "Maps/MrMrRogers.EchoReef_MaeTheatre",
        "MapProperties": {
          "Warp": "9 30 MrMrRogers.EchoReef_Graveyard 41 20 10 30 MrMrRogers.EchoReef_Graveyard 41 20"
        }
      },
      {
          "Action": "EditData",
          "Target": "Data/Characters",
          "Entries": {
            "MrMrRogers.EchoReef_Mae": {
              "DisplayName": "{{i18n:Mae}}",
              "BirthSeason": "Spring",
              "BirthDay": 6,
              "HomeRegion": "Other",
              "Language": "Default",
              "Gender": "Female",
              "Age": "Adult",
              "Manner": "Neutral",
              "SocialAnxiety": "Outgoing",
              "Optimism": "Neutral",
              "IsDarkSkinned": false,
              "CanBeRomanced": false,
              "Calendar": "HiddenAlways",
              "SocialTab": "HiddenUntilMet",
              "CanSocialize": true,
              "CanReceiveGifts": true,
              "CanGreetNearbyCharacters": true,
              "CanCommentOnPurchasedShopItems": true,
              "CanVisitIsland": false,
              "IntroductionsQuest": false,
              "ItemDeliveryQuests": false,
              "PerfectionScore": false,
              "EndSlideShow": "MainGroup",
              "SpouseAdopts": null,
              "SpouseWantsChildren": true,
              "SpouseGiftJealousy": false,
              "SpouseRoom": {},
              "SpousePatio": {},
              "SpouseFloors": [],
              "SpouseWallpapers": [],
              "DumpsterDiveFriendshipEffect": -25,
              "DumpsterDiveEmote": 8,
              "FriendsAndFamily": {},
              "FlowerDanceCanDance": null,
              "WinterStarGifts": [],
              "WinterStarParticipant": false,
              "UnlockConditions": null,
              "SpawnIfMissing": true,
              "Home": [
                {
                  "Id": "Default",
                  "Condition": null,
                  "Location": "MrMrRogers.EchoReef_MaeHouse",
                  "Tile": {
                    "X": 3,
                    "Y": 4
                  },
                  "Direction": "down"
                }
              ],
              "TextureName": null,
              "Appearance": [
                {
                  "Id": "MrMrRogers.EchoReef_Mae",
                  "Condition": null,
                  "Season": null,
                  "Indoors": true,
                  "Outdoors": true,
                  "Portrait": "Portraits/MrMrRogers.EchoReef_Mae",
                  "Sprite": "Characters/MrMrRogers.EchoReef_Mae",
                  "IsIslandAttire": false,
                  "Precedence": 0,
                  "Weight": 0
                }
              ],
              "MugShotSourceRect": null,
              "Size": {
                "X": 16,
                "Y": 32
              },
              "Breather": true,
              "BreathChestRect": null,
              "BreathChestPosition": null,
              "Shadow": null,
              "EmoteOffset": {
                "X": 0,
                "Y": 0
              },
              "ShakePortraits": null,
              "KissSpriteIndex": 28,
              "KissSpriteFacingRight": true,
              "FormerCharacterNames": [],
              "CustomFields": null
            }
          }
      },
      { 
            "Action": "Load",
            "Target": "Characters/Dialogue/MrMrRogers.EchoReef_Mae",
            "FromFile": "assets/blank.json"
        },
        {
          "Action": "Load",
          "Target": "Characters/schedules/MrMrRogers.EchoReef_Mae",
          "FromFile": "assets/blank.json"
        },
        {
            "Action": "EditData",
            "Target": "Data/NPCGiftTastes",
            "Entries": {
                "MrMrRogers.EchoReef_Mae": "{{i18n:MaeGiftLoveResponse}}//{{i18n:MaeGiftLikeResponse}}//{{i18n:MaeGiftDislikeResponse}}//{{i18n:MaeGiftHateResponse}}//{{i18n:MaeGiftNeutralResponse}}//"
            }
        },
        {
          "Action": "EditData",
          "Target": "Characters/Dialogue/MrMrRogers.EchoReef_Mae",
          "Entries": {
            "Introduction": "{{i18n:Mae_Introduction}}",
            "AcceptBirthdayGift_Positive": "{{i18n:Mae_AcceptBirthdayGift_Positive}}",
            "AcceptBirthdayGift_Negative": "{{i18n:Mae_AcceptBirthdayGift_Negative}}",
            "AcceptGift_(O)StardropTea": "{{i18n:Mae_AcceptGift_(O)StardropTea}}",
            "DumpsterDiveComment": "{{i18n:Mae_DumpsterDiveComment}}",
            "HitBySlingshot": "{{i18n:Mae_HitBySlingshot}}",
            "Mon": "{{i18n:Mae_{{Random: 1, 2, 3, 4, 5, 6, 7, 8, 9, 10}}}}",
            "Tue": "{{i18n:Mae_{{Random: 1, 2, 3, 4, 5, 6, 7, 8, 9, 10}}}}",
            "Wed": "{{i18n:Mae_{{Random: 1, 2, 3, 4, 5, 6, 7, 8, 9, 10}}}}",
            "Thu": "{{i18n:Mae_{{Random: 1, 2, 3, 4, 5, 6, 7, 8, 9, 10}}}}",
            "Fri": "{{i18n:Mae_{{Random: 1, 2, 3, 4, 5, 6, 7, 8, 9, 10}}}}",
            "Sat": "{{i18n:Mae_{{Random: 1, 2, 3, 4, 5, 6, 7, 8, 9, 10}}}}",
            "Sun": "{{i18n:Mae_{{Random: 1, 2, 3, 4, 5, 6, 7, 8, 9, 10}}}}"
          }
        },
        {
          "Action": "EditData",
          "Target": "Data/animationdescriptions",
          "Entries": {
            "MrMrRogers.EchoReef_Mae_sleep": "19/19/19",
            "mrmrrogers.echoreef_mae_sleep": "19/19/19"
          } 
        },
        {
          "Action": "EditData",
          "Target": "Characters/schedules/MrMrRogers.EchoReef_Mae",
          "Entries": {
            "spring": "600 MrMrRogers.EchoReef_MaeHouse 3 4 2/800 MrMrRogers.EchoReef_Arena 18 6 2/2200 MrMrRogers.EchoReef_MaeHouse 3 4 2 MrMrRogers.EchoReef_Mae_sleep"
          }
        }
  ]
}