{
  "Changes": [
	{	//Base das Artes
      "Action": "Load",
      "Target": "Characters/Lee",
      "FromFile": "Ativos/Personagens/Artes/Lee/Boneco/Le.Spring.png"
    },
	{
      "Action": "Load",
      "Target": "Portraits/Lee",
      "FromFile": "Ativos/Personagens/Artes/Lee/Retrato/Le.Spring.png"
    },
	{	//Artes
      "Action": "Load",
      "Target": "Characters/Le.Summer, Characters/Le.Fall, Characters/Le.Winter",
      "FromFile": "Ativos/Personagens/Artes/Lee/Boneco/{{TargetWithoutPath}}.png"
    },
	{
      "Action": "Load",
      "Target": "Portraits/Le.Summer, Portraits/Le.Fall, Portraits/Le.Winter",
      "FromFile": "Ativos/Personagens/Artes/Lee/Retrato/{{TargetWithoutPath}}.png"
    },
	{	// Lee
        "Action": "EditData",
        "Target": "Data/Characters",
		"Update": "OnDayStart",
        "Entries": {
			"Lee": { "DisplayName": "{{i18n:Lee.Display.Name}}", "Age": "child", "Manner": "polite", "SocialAnxiety": "neutral", "Optimism": "Positive", "Gender": "male", "CanBeRomanced": false, "CanGreetNearbyCharacters": false, "LoveInterest": "null", "ExcludeFromPerfectionScore": true, "BirthSeason": "summer", "BirthDay": 20, "Calendar": "HiddenAlways", "WinterStarParticipant": "false", "CanVisitIsland": "false",
            "Home": [ { "Id": "Ilha", "Location": "Ilha", "Tile": { "X": 5, "Y": 6 }, "Direction": "Down" } ],
			"Appearance": [ 
					{ "Season": "Spring", "Sprite": "Characters/Lee", "Portrait": "Portraits/Lee" },
					{ "Season": "Summer", "Sprite": "Characters/Le.Summer", "Portrait": "Portraits/Le.Summer" },
					{ "Season": "Fall", "Sprite": "Characters/Le.Fall", "Portrait": "Portraits/Le.Fall" },
					{ "Season": "Winter", "Sprite": "Characters/Le.Winter", "Portrait": "Portraits/Le.Winter" }
				]
			}
        }
    },
	{
		"Action": "EditData",
        "Target": "Data/Characters",
        "Update": "OnDayStart",
        "Fields": { "Lee": { "Calendar": "HiddenUntilMet", "Home": [ { "Id": "Casa.Interior", "Location": "Casa.Interior", "Tile": { "X": 18, "Y": 5 }, "Direction": "Down" } ] } },
        "When": { "HasSeenEvent: anyPlayer|contains=90105264": "true", "HasSeenEvent: anyPlayer|contains=58614300": "false", "HasSeenEvent: anyPlayer|contains=91105264": "false" }
    }
  ]
}