{
	"$schema": "https://smapi.io/schemas/content-patcher.json",
	"Changes": [
		{
			"LogName": "Honeyfuggle basic dialogue",
            "Action": "EditData",
            "Target": "Characters/Dialogue/{{Honeyfuggle}}",
			"Entries": {
			//Daily dialogue
				//0 hearts
				"Sun": "{{i18n:Sun}}",
				"Mon": "{{i18n:Mon}}",
				"Tue": "{{i18n:Tue}}",
				"Wed": "{{i18n:Wed}}",
				"Thu": "{{i18n:Thu}}",
				"Fri": "{{i18n:Fri}}",
				"Sat": "{{i18n:Sat}}",
				"summer_Sun": "{{i18n:summer_Sun}}",

				//2 hearts
				"Sun2": "{{i18n:Sun2}}",
				"Mon2": "{{i18n:Mon2}}",
				"Tue2": "{{i18n:Tue2}}",
				"Wed2": "{{i18n:Wed2}}",
				"Thu2": "{{i18n:Thu2}}",
				"Fri2": "{{i18n:Fri2}}",
				"Sat2": "{{i18n:Sat2}}",

				//4 hearts
				"Sun4": "{{i18n:Sun4}}",
				"Mon4": "{{i18n:Mon4}}",
				"Tue4": "{{i18n:Tue4{{LewisStatue}}}}",
				"Wed4": "{{i18n:Wed4}}",
				"Thu4": "{{i18n:Thu4}}",
				"Fri4": "{{i18n:Fri4.1}}#$q Vinilla.Honeyfuggle_1/Vinilla.Honeyfuggle_2 Fri4_old#{{i18n:Fri4.2}}#$r Vinilla.Honeyfuggle_1 20 Fri4_Vinilla.Honeyfuggle_1#{{i18n:Fri4.3}}#$r Vinilla.Honeyfuggle_2 0 Fri4_Vinilla.Honeyfuggle_2#{{i18n:Fri4.4}}",
				"Fri4_old": "{{i18n:Fri4_old}}",
				"Fri4_{{ModId}}_1": "{{i18n:Fri4_{{ModId}}_1}}",
				"Fri4_{{ModId}}_2": "{{i18n:Fri4_{{ModId}}_2}}",
				"Sat4": "{{i18n:Sat4}}",

				//6 hearts
				"Sun6": "{{i18n:Sun6}}",
				"Mon6": "{{i18n:Mon6}}",
				"Tue6": "{{i18n:Tue6}}",
				"Wed6": "{{i18n:Wed6}}",
				"Thu6": "{{i18n:Thu6}}",
				"Fri6": "{{i18n:Fri6}}",
				"Sat6": "{{i18n:Sat6{{RazzyGender}}}}",
				"spring_Mon6": "{{i18n:spring_Mon6}}",

				//8 hearts
				"Sun8": "{{i18n:Sun8}}",
				"Mon8": "{{i18n:Mon8}}",
				"Tue8": "{{i18n:Tue8{{LewisStatue}}}}",
				"Wed8": "{{i18n:Wed8}}",
				"Thu8": "{{i18n:Thu8}}",
				"Fri8": "{{i18n:Fri8}}",
				"Sat8": "{{i18n:Sat8}}",
				"spring_Tue8": "{{i18n:spring_Tue8}}",
				"spring_Sat8": "{{i18n:spring_Sat8.1}}[154 286 766 814]#$b#{{i18n:spring_Sat8.2}}",				
				"summer_Mon8": "{{i18n:summer_Mon8}}",
				"summer_Sat8": "{{i18n:summer_Sat8}}",
				"fall_Thu8": "{{i18n:fall_Thu8}}",
				"fall_Sun8": "{{i18n:fall_Sun8}}",
				"winter_Wed8": "{{i18n:winter_Wed8}}",
				"winter_Fri8": "{{i18n:winter_Fri8}}",

				//10 hearts
				"Sun10": "{{i18n:Sun10}}",
				"Mon10": "{{i18n:Mon10}}",
				"Tue10": "{{i18n:Tue10}}",
				"Wed10": "{{i18n:Wed10}}",
				"Thu10": "{{i18n:Thu10}}",
				"Fri10": "{{i18n:Fri10}}",
				"Sat10": "{{i18n:Sat10}}",
				"spring_Mon10": "{{i18n:spring_Mon10}}",
				"spring_Wed10": "{{i18n:spring_Wed10}}",
				"summer_Thu10": "{{i18n:summer_Thu10}}",
				"summer_Fri10": "{{i18n:summer_Fri10}}",
				"fall_Wed10": "{{i18n:fall_Wed10}}",
				"fall_Fri10": "{{i18n:fall_Fri10}}",
				"winter_Sun10": "{{i18n:winter_Sun10}}",
				"winter_Fri10": "{{i18n:winter_Thu10}}",

				//Day-specific
				"spring_1": "{{i18n:spring_1}}",
				"spring_12": "{{i18n:spring_12}}",
				"spring_23": "{{i18n:spring_23}}",
				"summer_1": "{{i18n:summer_1}}",
				"summer_10": "{{i18n:summer_10}}",
				"summer_27": "{{i18n:summer_27{{RazzyGender}}}}",
				"fall_1": "{{i18n:fall_1}}",
				"fall_15": "{{i18n:fall_15}}",
				"fall_26": "{{i18n:fall_26}}",
				"winter_1": "{{i18n:winter_1}}",
				"winter_7": "{{i18n:winter_7}}",
				"winter_24": "{{i18n:winter_24{{Solstice}}}}",

			//Conversation topics
				//Vanilla
				"wonGrange": "{{i18n:wonGrange}}",
				"cc_Bus": "{{i18n:cc_Bus}}",
				"cc_Bridge": "{{i18n:cc_Bridge}}",
				"cc_Complete": "{{i18n:cc_Complete}}",
				"movieTheater": "{{i18n:movieTheater}}",
				"pamHouseUprage": "{{i18n:pamHouseUprage}}",
				"pamHouseUpgradeAnonymous": "{{i18n:pamHouseUpgradeAnonymous}}",
				"GreenRain": "{{i18n:GreenRain}}",
				"GreenRainFinished": "{{i18n:GreenRainFinished}}",
				"GreenRain_2": "{{i18n:GreenRain_2}}",

				//Honeyfuggle
				"{{ModId}}_Arrival": "{{i18n:{{ModId}}_Arrival}}",
				"{{ModId}}_MagicTrick": "{{i18n:{{ModId}}_MagicTrick}}",

			//Gifting and reactions
				"AcceptBirthdayGift_Loved": "{{i18n:AcceptBirthdayGift_Loved}}",
				"AcceptBirthdayGift_Positive": "{{i18n:AcceptBirthdayGift_Positive}}",
				"AcceptBirthdayGift": "{{i18n:AcceptBirthdayGift}}",
				"AcceptBirthdayGift_Negative": "{{i18n:AcceptBirthdayGift_Negative}}",
				"AcceptGift_(O)66": "{{i18n:AcceptGift_(O)66}}",
				"AcceptGift_(O)104": "{{i18n:AcceptGift_(O)104}}",
				"AcceptGift_(O)340": "{{i18n:AcceptGift_(O)340}}",
				"AcceptGift_(O)124": "{{i18n:AcceptGift_(O)124}}",
				"AcceptGift_(O)110": "{{i18n:AcceptGift_JunkArtifact}}",
				"AcceptGift_(O)111": "{{i18n:AcceptGift_JunkArtifact}}",
				"AcceptGift_(O)112": "{{i18n:AcceptGift_JunkArtifact}}",
				"AcceptGift_(O)105": "{{i18n:AcceptGift_JunkArtifact}}",
				"AcceptGift_(O)StardropTea": "{{i18n:AcceptGift_(O)StardropTea}}",
				"RejectMovieTicket": "{{i18n:RejectMovieTicket}}",
				"RejectBouquet_NotDatable": "{{i18n:RejectBouquet}}",
				"DumpsterDiveComment": "{{i18n:DumpsterDiveComment}}",

			//Island stuff
				"Resort_Entering": "{{i18n:Resort_Entering}}",
				"Resort": "{{i18n:Resort}}",
				"Resort_Leaving": "{{i18n:Resort_Leaving}}"
			}
		},
		{
			"LogName": "10 heart event dialogue edit",
			"Action": "EditData",
			"Target": "Characters/Dialogue/{{Honeyfuggle}}",
			"Entries": {
				"Sun10": "{{i18n:Sun10.Event.{{MaskOn}}}}",
				"Mon10": "{{i18n:Mon10.Event}}",
				"Tue10": "{{i18n:Tue10.Event}}",
				"Wed10": "{{i18n:Wed10.Event}}",
				"Thu10": "{{i18n:Thu10.Event}}",
				"Fri10": "{{i18n:Fri10.Event}}",
				"Sat10": "{{i18n:Sat10.Event}}",
				"spring_Tue10": "{{i18n:spring_Tue10.Event}}",
				"spring_Thu10": "{{i18n:spring_Thu10.Event}}",
				"summer_Tue10": "{{i18n:summer_Tue10.Event}}",
				"summer_Wed10": "{{i18n:summer_Wed10.Event}}",
				"summer_Thu10": "{{i18n:summer_Thu10.Event}}",
				"summer_Fri10": "{{i18n:summer_Fri10.Event}}",
				"fall_Mon10": "{{i18n:fall_Mon10.Event}}",
				"fall_Thu10": "{{i18n:fall_Thu10.Event}}",
				"fall_Fri10": "{{i18n:fall_Fri10.Event}}",
				"winter_Mon10": "{{i18n:winter_Mon10.Event}}",
				"winter_Tue10": "{{i18n:winter_Tue10.Event}}"
			},
			"When": {
				"HasSeenEvent": "{{ModId}}_10Heart"
			}
		},

		//Schedule strings
		{
			"LogName": "Honeyfuggle schedule strings",
            "Action": "EditData",
		  	"Target": "Strings/Schedules/{{Honeyfuggle}}",
            "Entries": {
				"{{ModId}}_Wizard": "{{i18n:Wizard.1}}",
				"{{ModId}}_Gunther": "{{i18n:Gunther}}",
				"{{ModId}}_Saloon": "{{i18n:Saloon}}",
				"{{ModId}}_Beach": "{{i18n:Beach}}",
				"{{ModId}}_NightMarket": "{{i18n:NightMarket}}"
			}
		},
		{
			"LogName": "Wizard schedule string",
			"Action": "EditData",
			"Target": "Strings/Schedules/Wizard",
			"Entries": {
				"{{ModId}}_Wizard": "{{i18n:{{ModId}}_Wizard.2.{{Random:Neutral,Fem,Masc}}}}"

			}
		},

		//Other
		{	
			"LogName": "Rain dialogue",
			"Action": "EditData",
			"Target": "Characters/Dialogue/rainy",
			"Entries": {
				"{{Honeyfuggle}}": "{{i18n:rain.{{Random:1,2,3}}}}"
			}
		},
		{
			"LogName": "Desert festival string",
      		"Action": "EditData",
      		"Target": "Strings/1_6_Strings",
      		"Entries": {
				"DesertFestival_{{Honeyfuggle}}": "{{i18n:DesertFestival}}",
	  		}
		},
		{
			"LogName": "Movie invite dialogue",
			"Action": "EditData",
			"Target": "Strings/Characters",
			"Entries": {
			 	"MovieInvite_Invited_{{Honeyfuggle}}": "{{i18n:MovieInvite_Invited}}",
			}
		},

		//Conversation topics - Vanilla NPCs
		{
			"LogName": "Intro event CTs",
			"Action": "EditData",
			"Target": "Characters/Dialogue/Lewis, Characters/Dialogue/Wizard, Characters/Dialogue/Marnie, Characters/Dialogue/Linus",
			"Entries": {
				"{{ModId}}_Arrival": "{{i18n:{{ModId}}_Arrival.{{TargetWithoutPath}}.{{Random:Neutral,Fem,Masc|key={{TargetWithoutPath}}}}}}"
			}
		},
		{
			"LogName": "2 heart event CTs - part one",
			"Action": "EditData",
			"Target": "Characters/Dialogue/Elliott, Characters/Dialogue/Abigail",
			"Entries": {
				"{{ModId}}_MagicTrick": "{{i18n:{{ModId}}_MagicTrick.{{TargetWithoutPath}}.{{Random:Neutral,Fem,Masc|key={{TargetWithoutPath}}}}}}"
			}
		},
		{
			"LogName": "2 heart event CTs - part two",
			"Action": "EditData",
			"Target": "Characters/Dialogue/Emily",
			"Entries": {
				"{{ModId}}_MagicTrick": "{{i18n:{{ModId}}_MagicTrick.{{TargetWithoutPath}}}}"
			}
		},
		{
			"LogName": "10 heart event CTs - part one",
			"Action": "EditData",
			"Target": "Characters/Dialogue/Wizard, Characters/Dialogue/Lewis, Characters/Dialogue/Caroline, Characters/Dialogue/Jodi, Characters/Dialogue/Marnie, Characters/Dialogue/George",
			"Entries": {
				"{{ModId}}_Departure": "{{i18n:{{ModId}}_Departure.{{TargetWithoutPath}}.{{Random:Neutral,Fem,Masc|key={{TargetWithoutPath}}}}}}"
			}
		},
		{
			"LogName": "10 heart event CTs - part two",
			"Action": "EditData",
			"Target": "Characters/Dialogue/Jodi, Characters/Dialogue/George",
			"Entries": {
				"{{ModId}}_Departure": "{{i18n:{{ModId}}_Departure.{{TargetWithoutPath}}}}"
			}
		},

		//Lasting Conversation Topics
		{
			"LogName": "LCT intro",
			"Action": "EditData",
			"Target": "sophie.ConversationTopics",
			"Entries": {
				"{{ModId}}_Arrival": "true"
			},
			"When": {
				"HasConversationTopic": "{{ModId}}_Arrival"
			}
		},
		{
			"LogName": "LCT 2 heart",
			"Action": "EditData",
			"Target": "sophie.ConversationTopics",
			"Entries": {
				"{{ModId}}_MagicTrick": "true"
			},
			"When": {
				"HasConversationTopic": "{{ModId}}_MagicTrick"
			}
		},
		{
			"LogName": "LCT 10 heart",
			"Action": "EditData",
			"Target": "sophie.ConversationTopics",
			"Entries": {
				"{{ModId}}_Departure": "true"
			},
			"When": {
				"HasConversationTopic": "{{ModId}}_Departure"
			}
		}
	]
}